fnapy/__init__.py
fnapy/compat.py
fnapy/config.py
fnapy/connection.py
fnapy/exceptions.py
fnapy/fnapy_manager.py
fnapy/utils.py
tests/__init__.py
tests/test_connection.py
tests/test_http_messages.py
tests/test_query.py
tests/test_utils.py
tests/offline/__init__.py
tests/offline/test_batch.py
tests/offline/test_carriers.py
tests/offline/test_client_order_comments.py
tests/offline/test_encoding.py
tests/offline/test_incidents.py
tests/offline/test_manager.py
tests/offline/test_messages.py
tests/offline/test_offers.py
tests/offline/test_orders.py
tests/offline/test_pricing.py
tests/offline/test_shop_invoices.py
tests/online/__init__.py
tests/online/old_test_fnapy_manager.py
tests/online/test_batch.py
tests/online/test_carriers.py
tests/online/test_client_order_comments.py
tests/online/test_incidents.py
tests/online/test_messages.py
tests/online/test_offers.py
tests/online/test_orders.py
tests/online/test_pricing.py
tests/online/test_shop_invoices.py
fnapy-1.4.2.dist-info/AUTHORS.rst
fnapy-1.4.2.dist-info/LICENSE.txt
fnapy-1.4.2.dist-info/METADATA
fnapy-1.4.2.dist-info/WHEEL
fnapy-1.4.2.dist-info/top_level.txt
fnapy-1.4.2.dist-info/zip-safe
fnapy-1.4.2.dist-info/RECORD
