Metadata-Version: 2.1
Name: fnapy
Version: 1.4.2
Summary: A Python API for FNAC WebServices
Home-page: https://github.com/alexandriagroup/fnapy
Author: Taurus Olson
Author-email: taurusolson@gmail.com
License: MIT
Keywords: api,fnac,python,webservices
Classifier: Development Status :: 4 - Beta
Classifier: Intended Audience :: Developers
Classifier: License :: OSI Approved :: MIT License
Classifier: Programming Language :: Python :: 2
Classifier: Programming Language :: Python :: 3
Classifier: Programming Language :: Python :: Implementation :: CPython
Classifier: Topic :: Software Development :: Libraries :: Python Modules
License-File: LICENSE.txt
License-File: AUTHORS.rst
Requires-Dist: requests
Requires-Dist: xmltodict
Requires-Dist: lxml
